{
  "groups": [
    {
      "name": "app",
      "type": "config.AppProperties",
      "sourceType": "config.AppProperties"
    },
    {
      "name": "app.auth",
      "type": "config.AppProperties$Auth",
      "sourceType": "config.AppProperties",
      "sourceMethod": "getAuth()"
    },
    {
      "name": "app.oauth2",
      "type": "config.AppProperties$OAuth2",
      "sourceType": "config.AppProperties",
      "sourceMethod": "getOauth2()"
    }
  ],
  "properties": [
    {
      "name": "app.auth.token-expiration-msec",
      "type": "java.lang.Long",
      "sourceType": "config.AppProperties$Auth"
    },
    {
      "name": "app.auth.token-secret",
      "type": "java.lang.String",
      "sourceType": "config.AppProperties$Auth"
    },
    {
      "name": "app.oauth2.authorized-redirect-uris",
      "type": "java.util.List<java.lang.String>",
      "sourceType": "config.AppProperties$OAuth2"
    }
  ],
  "hints": []
}